omnipyseed/__init__.py
omnipyseed/set_manual_seeds.py
omnipyseed-0.0.4.dist-info/LICENSE
omnipyseed-0.0.4.dist-info/METADATA
omnipyseed-0.0.4.dist-info/WHEEL
omnipyseed-0.0.4.dist-info/top_level.txt
omnipyseed-0.0.4.dist-info/RECORD
