Metadata-Version: 2.1
Name: omnipyseed
Version: 0.0.4
Summary: A tiny package for seeding all the RNGs in numerical experiments
Home-page: https://github.com/gdetor/omnipyseed
Author: Georgios Is. Detorakis
Author-email: gdetor@protonmail.ch
Project-URL: Bug Tracker, https://github.com/gdetor/omnipyseed/issues
Classifier: Programming Language :: Python :: 3
Classifier: License :: OSI Approved :: GNU General Public License v3 or later (GPLv3+)
Classifier: Operating System :: OS Independent
Requires-Python: >=3.6
License-File: LICENSE
